uvicorn_extended/__init__.py
uvicorn_extended/py.typed
uvicorn_extended-0.0.0.dist-info/METADATA
uvicorn_extended-0.0.0.dist-info/WHEEL
uvicorn_extended-0.0.0.dist-info/RECORD
